personalization_profiles/AdventurousTraveler.py
personalization_profiles/BudgetTraveler.py
personalization_profiles/BusinessTraveler.py
personalization_profiles/EcoTraveler.py
personalization_profiles/FamilyTraveler.py
personalization_profiles/PersonaManager.py
personalization_profiles/PersonaType.py
personalization_profiles/PersonalizationProfile.py
personalization_profiles/User.py
personalization_profiles/__init__.py
personalization_profiles-0.1.4.dist-info/METADATA
personalization_profiles-0.1.4.dist-info/WHEEL
personalization_profiles-0.1.4.dist-info/top_level.txt
personalization_profiles-0.1.4.dist-info/RECORD
