Metadata-Version: 2.1
Name: personalization_profiles
Version: 0.1.4
License: MIT
Requires-Python: >=3.9
Requires-Dist: numpy >=1.20
Requires-Dist: langchain
